{
  "id": 591,
  "timestamp": "2018-03-14T20:31:46-01:00",
  "customerId": 16,
  "items": [
    {
      "name": "\"szynka 1kg\"",
      "quantity": 5,
      "price": 30.0
    },
    {
      "name": "\"woda 1.5l\"",
      "quantity": 5,
      "price": 2.0
    },
    {
      "name": "\"jajko\"",
      "quantity": 20,
      "price": 0.5
    },
    {
      "name": "\"woda gazowana 1.5l\"",
      "quantity": 10,
      "price": 2.1
    },
    {
      "name": "\"chleb ciemny\"",
      "quantity": 26,
      "price": 2.5
    },
    {
      "name": "\"szynka 1kg\"",
      "quantity": 11,
      "price": 30.0
    },
    {
      "name": "\"chleb ciemny\"",
      "quantity": 15,
      "price": 2.5
    },
    {
      "name": "\"mleko 3% 1l\"",
      "quantity": 5,
      "price": 2.3
    }
  ],
  "sum": 635.0
}