{
  "id": 277,
  "timestamp": "2018-03-14T20:34:40-01:00",
  "customerId": 15,
  "items": [
    {
      "name": "\"szynka 1kg\"",
      "quantity": 24,
      "price": 30.0
    },
    {
      "name": "\"masło\"",
      "quantity": 28,
      "price": 5.0
    },
    {
      "name": "\"masło\"",
      "quantity": 19,
      "price": 5.0
    },
    {
      "name": "\"chleb ciemny\"",
      "quantity": 15,
      "price": 2.5
    },
    {
      "name": "\"szynka 1kg\"",
      "quantity": 13,
      "price": 30.0
    },
    {
      "name": "\"woda 1.5l\"",
      "quantity": 19,
      "price": 2.0
    },
    {
      "name": "\"chleb ciemny\"",
      "quantity": 27,
      "price": 2.5
    },
    {
      "name": "\"masło\"",
      "quantity": 12,
      "price": 5.0
    },
    {
      "name": "\"masło\"",
      "quantity": 20,
      "price": 5.0
    },
    {
      "name": "\"masło\"",
      "quantity": 19,
      "price": 5.0
    },
    {
      "name": "\"chleb ciemny\"",
      "quantity": 28,
      "price": 2.5
    }
  ],
  "sum": 1813.0
}