{
  "id": 93,
  "timestamp": "2018-03-14T19:42-01:00",
  "customerId": 7,
  "items": [
    {
      "name": "\"jajko\"",
      "quantity": 20,
      "price": 0.5
    },
    {
      "name": "\"masło\"",
      "quantity": 12,
      "price": 5.0
    },
    {
      "name": "\"chleb biały\"",
      "quantity": 21,
      "price": 2.2
    },
    {
      "name": "\"woda gazowana 1.5l\"",
      "quantity": 2,
      "price": 2.1
    },
    {
      "name": "\"masło\"",
      "quantity": 16,
      "price": 5.0
    },
    {
      "name": "\"chleb ciemny\"",
      "quantity": 24,
      "price": 2.5
    },
    {
      "name": "\"jajko\"",
      "quantity": 23,
      "price": 0.5
    },
    {
      "name": "\"mleko 3% 1l\"",
      "quantity": 28,
      "price": 2.3
    },
    {
      "name": "\"chleb ciemny\"",
      "quantity": 3,
      "price": 2.5
    }
  ],
  "sum": 343.79999999999995
}